winui2/_winui2_microsoft_ui_xaml_controls.cp311-win32.pyd
winui2/_winui2_microsoft_ui_xaml_controls.pyi
winui2/microsoft/ui/xaml/controls/__init__.py
winui2/microsoft/ui/xaml/controls/py.typed
winui2_microsoft_ui_xaml_controls-3.2.1.dist-info/METADATA
winui2_microsoft_ui_xaml_controls-3.2.1.dist-info/WHEEL
winui2_microsoft_ui_xaml_controls-3.2.1.dist-info/top_level.txt
winui2_microsoft_ui_xaml_controls-3.2.1.dist-info/RECORD
