Metadata-Version: 2.4
Name: winui2-Microsoft.UI.Xaml.Controls
Version: 3.2.1
Summary: Python projection of Windows Runtime (WinRT) APIs
License-Expression: MIT
Project-URL: Documentation, https://pywinrt.readthedocs.io
Project-URL: Repository, https://github.com/pywinrt/pywinrt
Project-URL: Changelog, https://github.com/pywinrt/pywinrt/blob/main/CHANGELOG.md
Classifier: Operating System :: Microsoft :: Windows
Classifier: Programming Language :: Python :: 3
Classifier: Programming Language :: Python :: Implementation :: CPython
Classifier: Intended Audience :: Developers
Requires-Python: >=3.9
Requires-Dist: winrt-runtime~=3.2.1.0
Requires-Dist: winrt-Windows.UI.Xaml~=3.2.1.0
Requires-Dist: winrt-Windows.UI.Xaml.Controls~=3.2.1.0
Requires-Dist: winrt-Windows.UI.Xaml.Controls.Primitives~=3.2.1.0
Provides-Extra: all
Requires-Dist: webview2-Microsoft.Web.WebView2.Core[all]~=3.2.1.0; extra == "all"
Requires-Dist: winrt-Windows.ApplicationModel.Contacts[all]~=3.2.1.0; extra == "all"
Requires-Dist: winrt-Windows.ApplicationModel.DataTransfer[all]~=3.2.1.0; extra == "all"
Requires-Dist: winrt-Windows.Foundation[all]~=3.2.1.0; extra == "all"
Requires-Dist: winrt-Windows.Foundation.Collections[all]~=3.2.1.0; extra == "all"
Requires-Dist: winrt-Windows.Foundation.Numerics[all]~=3.2.1.0; extra == "all"
Requires-Dist: winrt-Windows.Globalization.NumberFormatting[all]~=3.2.1.0; extra == "all"
Requires-Dist: winrt-Windows.UI[all]~=3.2.1.0; extra == "all"
Requires-Dist: winrt-Windows.UI.Composition[all]~=3.2.1.0; extra == "all"
Requires-Dist: winrt-Windows.UI.Text[all]~=3.2.1.0; extra == "all"
Requires-Dist: winrt-Windows.UI.Xaml[all]~=3.2.1.0; extra == "all"
Requires-Dist: winrt-Windows.UI.Xaml.Controls[all]~=3.2.1.0; extra == "all"
Requires-Dist: winrt-Windows.UI.Xaml.Controls.Primitives[all]~=3.2.1.0; extra == "all"
Requires-Dist: winrt-Windows.UI.Xaml.Input[all]~=3.2.1.0; extra == "all"
Requires-Dist: winrt-Windows.UI.Xaml.Interop[all]~=3.2.1.0; extra == "all"
Requires-Dist: winrt-Windows.UI.Xaml.Media[all]~=3.2.1.0; extra == "all"
Requires-Dist: winrt-Windows.UI.Xaml.Media.Animation[all]~=3.2.1.0; extra == "all"
